Workbook

Sheet Cover
A31: Food_Lab
A34: Team X
B57: Team Member : | D57: 1 | E57: Cherry Phoo Phoo Khaing
D58: 2 | E58: Zaw Phyo Aung
D59: 3 | E59: Min Khant
D60: 4 | E60: Zayyar Htet
D61: 5 | E61: Aung Min Khant
D62: 6 | E62: Zarni Win Lwin
K63: Create Date | M63: 44555
K64: Update Date | M64: =NOW() -> 44662.727
D101: T_CU_Coin
C104: customer_id | D104: Customer ID
C105: coin | D105: Coin Balance
C106: approve_By | D106: Approve By

Sheet Customer Requirement
A1: Customer Requirement (要件定義) | C1: =Cover!A31 -> Food_Lab | O1: Create Date | P1: 44555
O2: Update Date | P2: =NOW() -> 44662.727
A5: Customer Requirement
C6: 1 | D6: Kitchen lab
D7: 1-1 | E7: Admin Page
E8: 1-1-1 | F8: Admin Page
F9: a) | G9: Login
F10: b) | G10: Transaction Manage
F11: c) | G11: Coin Manage | J11: Admin
F12: d) | G12: Finance Manage
F13: e) | G13: Product Manage
F14: f) | G14: Dashboard
D16: 2-1 | E16: Customer Page
E17: 2-1-1 | F17: Customer Page Inculde
F18: a) | G18: Login
F19: b) | G19: Buy Coin
F20: c) | G20: Buy Item
F21: d) | G21: Verify Mail
F22: e) | G22: Message/Notification
F23: f) | G23: Profile Setting
F24: g) | G24: Tracking
D26: 3-1 | E26: Kitchen Page
E27: 3-1-1 | F27: Kitchen Page Include
F28: a) | G28: Order Manage

Sheet Schedule
A1: Schedule (進捗） | C1: =Cover!A31 -> Food_Lab | M1: Create Date | N1: 44555
M2: Update Date | N2: =NOW() -> 44662.727
C4: No | D4: Sub | E4: Task | F4: Assign | G4: Est Start | H4: Est End | I4: Duration Day | J4: Act Start | K4: Act End | L4: Act Duration | M4: Work Done
C5: 1 | E5: Schedule（進捗） | F5: ALL | G5: 44557 | H5: 44647 | I5: =H5-G5 -> 90 | J5: 44556 | L5: =K5-J5 -> -44556 | M5: 0
C6: 2 | E6: Project Flow（流れ） | F6: Linn | G6: 44557 | H6: 44564 | I6: =H6-G6 -> 7 | J6: 44556 | K6: 44564 | L6: =K6-J6 -> 8 | M6: 1
C7: 3 | E7: Screen Design（画面設計） | F7: C,M,ZN | G7: 44564 | H7: 44571 | I7: =H7-G7 -> 7 | J7: 44557 | K7: 44570 | L7: =K7-J7 -> 13 | M7: 1
C8: 4 | E8: Database（DB設計書） | F8: Linn | G8: 44566 | H8: 44571 | I8: =H8-G8 -> 5 | J8: 44566 | K8: 44570 | L8: =K8-J8 -> 4 | M8: 1
C9: 5 | E9: Development（開発） | F9: ALL | G9: 44571 | H9: 44602 | I9: =H9-G9 -> 31 | J9: 44571 | L9: =K9-J9 -> -44571 | M9: =SUM(M10:M23)/14 -> 0.76785714
D10: 1 | E10: Home | F10: Min | G10: 44571 | H10: 44575 | I10: =H10-G10 -> 4 | J10: 44571 | L10: =K10-J10 -> -44571 | M10: 0.8
D11: 2 | E11: Product | F11: Cherry,Aung | G11: 44577 | H11: 44591 | I11: =H11-G11 -> 14 | J11: 44579 | L11: =K11-J11 -> -44579 | M11: 0.4
D12: 3 | E12: Buy Coin | F12: Zaw | G12: 44581 | H12: 44591 | I12: =H12-G12 -> 10 | J12: 44581 | L12: =K12-J12 -> -44581 | M12: 0.8
D13: 4 | E13: Access | F13: Min | G13: 44575 | H13: 44580 | I13: =H13-G13 -> 5 | J13: 44575 | L13: =K13-J13 -> -44575 | M13: 0.85
D14: 5 | E14: Inform | F14: Zayar | G14: 44571 | H14: 44576 | I14: =H14-G14 -> 5 | J14: 44584 | L14: =K14-J14 -> -44584 | M14: 0.8
D15: 6 | E15: Profile | F15: Zayar | G15: 44576 | H15: 44582 | I15: =H15-G15 -> 6 | J15: 44579 | L15: =K15-J15 -> -44579 | M15: 0.7
D16: 1 | E16: Access | F16: Min | G16: 44580 | H16: 44585 | I16: =H16-G16 -> 5 | J16: 44585 | L16: =K16-J16 -> -44585 | M16: 0.8
D17: 2 | E17: Dashboard | F17: Zarni | G17: 44571 | H17: 44574 | I17: =H17-G17 -> 3 | J17: 44571 | L17: =K17-J17 -> -44571 | M17: 0.8
D18: 3 | E18: Transaction | F18: Zarni | G18: 44574 | H18: 44580 | I18: =H18-G18 -> 6 | J18: 44571 | L18: =K18-J18 -> -44571 | M18: 0.8
D19: 4 | E19: Coin | F19: Linn | G19: 44581 | H19: 44591 | I19: =H19-G19 -> 10 | J19: 44578 | K19: 44579 | L19: =K19-J19 -> 1 | M19: 0.8
D20: 5 | E20: Customer | F20: Zarni | G20: 44580 | H20: 44585 | I20: =H20-G20 -> 5 | J20: 44571 | L20: =K20-J20 -> -44571 | M20: 0.8
D21: 6 | E21: Finance | F21: Cherry | G21: 44571 | H21: 44577 | I21: =H21-G21 -> 6 | J21: 44571 | L21: =K21-J21 -> -44571 | M21: 0.8
D22: 7 | E22: Product | F22: Aung | G22: 44571 | H22: 44581 | I22: =H22-G22 -> 10 | J22: 44576 | L22: =K22-J22 -> -44576 | M22: 0.8
D23: 8 | E23: Setting | F23: Zayar | G23: 44582 | H23: 44587 | I23: =H23-G23 -> 5 | J23: 44571 | L23: =K23-J23 -> -44571 | M23: 0.8
D24: 1 | E24: Access | F24: Linn | I24: =H24-G24 -> 0 | L24: =K24-J24 -> 0 | M24: 0
D25: 2 | E25: Order | F25: Linn | I25: =H25-G25 -> 0 | L25: =K25-J25 -> 0 | M25: 0
C26: 6 | E26: Unit Test（単体試験） | G26: 44602 | H26: 44612 | I26: =H26-G26 -> 10 | L26: =K26-J26 -> 0 | M26: 0
C27: 7 | E27: Integration Test（結合試験） | G27: 44612 | H27: 44617 | I27: =H27-G27 -> 5 | L27: =K27-J27 -> 0 | M27: 0
C28: 8 | E28: Hosting Dev | G28: 44617 | H28: 44623 | I28: =H28-G28 -> 6 | L28: =K28-J28 -> 0 | M28: 0
C29: 9 | E29: Hosting Public | G29: 44623 | H29: 44630 | I29: =H29-G29 -> 7 | L29: =K29-J29 -> 0 | M29: 0
C30: 10 | E30: Release | G30: 44265 | H30: 44275 | I30: =H30-G30 -> 10 | L30: =K30-J30 -> 0 | M30: 0
I31: =SUM(I6:I30) -> 182
H32: Month | I32: =I31/30 -> 6.0666667
D101: T_CU_Coin
C104: customer_id | D104: Customer ID
C105: coin | D105: Coin Balance
C106: approve_By | D106: Approve By

Sheet By person
A1: Schedule (進捗） | C1: =Cover!A31 -> Food_Lab | AJ1: Create Date | AK1: 44555
AJ2: Update Date | AK2: =NOW() -> 44662.727
B5: No | C5: Name | D5: 10 | E5: 11 | F5: 12 | G5: 13 | H5: 14 | I5: 15 | J5: 16 | K5: 17 | L5: 18 | M5: 19 | N5: 20 | O5: 21 | P5: 22 | Q5: 23 | R5: 24 | S5: 25 | T5: 26 | U5: 27 | V5: 28 | W5: 29 | X5: 30 | Y5: 31 | Z5: 1 | AA5: 2 | AB5: 3 | AC5: 4 | AD5: 5 | AE5: 6 | AF5: 7 | AG5: 8 | AH5: 9 | AI5: 10
B6: 1 | C6: Cherry | F6: Finance | P6: Product | Z6: Review & Repair
B7: 2 | C7: Min | F7: Home | J7: Access | O7: Access | T7: Mobile
B8: 3 | C8: Aung | H8: Product | R8: Product
B9: 4 | C9: Zaw/Linn | H9: Coin | S9: Coin
B10: 5 | C10: Zarni | E10: Dashboard | I10: Transaction | O10: Customer | T10: Mobile Design
B11: 6 | C11: Zayar | F11: Inform | K11: Profile | Q11: Setting | V11: Mobile
B12: 7 | C12: Linn

Sheet Coin & Order Flow
A1: Main Flow (プロジャック流れ） | C1: =Cover!A31 -> Food_Lab | S1: Create Date | T1: 44555
S2: Update Date | T2: =NOW() -> 44662.727
A4: Explanation of Project | D4: Coin & Order Flow
A5: プロジャックの説明
A10: (プロジャック流れ）
C13: Admin | K13: Customer | Q13: Kitchen
C24: No | E24: Yes
M33: Yes
K34: No
M42: COIN
N45: COD
C49: No | E49: Yes
D101: T_CU_Coin
C104: customer_id | D104: Customer ID
C105: coin | D105: Coin Balance
C106: approve_By | D106: Approve By

Sheet Project Flow_Admin
A1: Main Flow (プロジャック流れ） | C1: =Cover!A31 -> Food_Lab | O1: Create Date | P1: 44555
O2: Update Date | P2: =NOW() -> 44662.727
A4: Explanation of Project | D4: Admin Page
A5: プロジャックの説明
A10: (プロジャック流れ）
B13: Path： | C13: http:domain/admin/ | O13: Super Admin
O15: Main Category
O16: Function
O17: Page

Sheet Project Flow_Customer
A1: Main Flow (プロジャック流れ） | C1: =Cover!A31 -> Food_Lab | R1: Create Date | S1: 44555
R2: Update Date | S2: =NOW() -> 44662.727
A4: Explanation of Project | D4: Customer page (Home)
A5: プロジャックの説明
A10: (プロジャック流れ）
B13: Path： | C13: http:domain/

Sheet Project Flow_Kitchen
A1: Main Flow (プロジャック流れ） | C1: =Cover!A31 -> Food_Lab | S1: Create Date | T1: 44555
S2: Update Date | T2: =NOW() -> 44662.727
A4: Explanation of Project | D4: Kitchen Page
A5: プロジャックの説明
A10: (プロジャック流れ）
B13: Path： | C13: http:domain/order

Sheet Screen Design
A1: Screen Design (画面設計） | C1: =Cover!A31 -> Food_Lab | O1: Create Date | P1: 44555
O2: Update Date | P2: =NOW() -> 44662.727
A5: Screen Name ： | D5: Admin Login Screen

Sheet Code Rule
A1: Code Rule | C1: =Cover!A31 -> Food_Lab | O1: Create Date | P1: 44555
O2: Update Date | P2: =NOW() -> 44662.727
B5: Global Rule
C6: 1 | D6: Camel Naming Rule for all Function
C7: 2 | D7: Max Code line: 170 line in one method
C8: 3 | D8: Max Argument : 7 parameter in one function
C9: 4 | D9: ALL Capatial Letter for global variable
C10: 5 | D10: Variable name must be meaningful (Not allow x,y,x,I,etc…)
C11: 6 | D11: Must write comment in every method (header)
D12: /*
D13: *Create:Author Name(Date)
D14: *Update:Author Name(Date)
D15: *Explanation of method or function
D16: *Parameter explain
D17: *Return
D18: */
C19: 7 | D19: Not allow 3 time nested Loop Condition
C20: 8 | D20: If using recursive method,must have break condition
C21: 9 | D21: Must be format.
B23: HTML Rule
C24: 1 | D24: Must write close tag
C25: 2 | D25: Must write comment for open close tag
C26: 3 | D26: Not allow inline css and internal css
C27: 4 | D27: ID must be unique in one html
B29: CSS Rule
C30: 1 | D30: Use scale unit (em,%,vh,vw) instead of px.(As much as possible)
C31: 2 | D31: Use root declear for common properties.
C32: 3 | D32: Must write comment by block
C33: 4 | D33: Not allow minus assign (Example : margin : -10px)
C34: 5 | D34: Must be responsive
B36: Javascript/Jquery Rule
C37: 1 | D37: Global varible must be write in start of line
C38: 2 | D38: If webpage is used jquery,Must be write (document.ready…)
C39: 3 | D39: Avoid Deadcode
B41: Json Rule
C42: 1 | D42: Key must be meaningful
B44: Ajax Rule
C45: 1 | D45: Must have ContectType,success,error catch and statuscode control
C46: 2 | D46: Must have timeout properties
C47: 3 | D47: ID must be encrypt
B49: Laravel
C50: 1 | D50: Log must be divided by Category
C51: 2 | D51: Must use try catch in complex business logic
C52: 3 | D52: Must use lang
C53: 4 | D53: Password must be encrypt
C54: 5 | D54: Class name Must be Pascal Naming Rule
C55: 6 | D55: View name Must be Camel Naming Rue
C56: 7 | D56: Avoid Deadcode
C57: 8 | D57: Must MVC Rule
C58: 9 | D58: Must be divided Validation Class
C59: 10 | D59: Class Inside Oncall function must be private
C60: 11 | D60: Must delete session if it is not use

Sheet DB Design
A1: DB Design (DB設計） | C1: =Cover!A31 -> Food_Lab | N1: Create Date | O1: 44555
N2: Update Date | O2: =NOW() -> 44662.727
B4: DB Name ： | D4: FOOD_LAB_DB
B6: Default Fields
B8: No | C8: Field Name | D8: Description | F8: PK | G8: AI | H8: NN | I8: Type | J8: Length | K8: FK | L8: Remark
B9: 1 | C9: id | D9: ID of Row | F9: ● | G9: ● | H9: ● | I9: Bigint
B10: 2 | C10: del_flg | D10: Deleted or Not | H10: ● | I10: integer | L10: 0:false , 1:true
B11: 3 | C11: created_at | D11: Created Timestamp | H11: ● | I11: timestamp
B12: 4 | C12: updated_at | D12: Updated Timestamp | I12: timestamp
B15: Table Name ： | D15: M_AD_Login
B17: No | C17: Field Name | D17: Description | F17: PK | G17: AI | H17: NN | I17: Type | J17: Length | K17: FK | L17: Remark
B18: 1 | C18: ad_name | D18: Name | H18: ● | I18: varchar | J18: 128
B19: 2 | C19: ad_password | D19: Password | H19: ● | I19: varchar | J19: 128
B20: 3 | C20: ad_role | D20: Role | H20: ● | I20: varchar | J20: 2 | L20: SA:Super Admin, AD:Admin, KA:Kitchen_Admin,DL:Delivery
B21: 4 | C21: ad_valid | D21: Valid or not | H21: ● | I21: integer | L21: 0:false , 1:true
B22: 5 | C22: ad_login_dt | D22: Last Login Time | I22: timestamp
B27: Table Name ： | D27: M_AD_CoinRate
B29: No | C29: Field Name | D29: Description | F29: PK | G29: AI | H29: NN | I29: Type | J29: Length | K29: FK | L29: Remark
B30: 1 | C30: base | D30: Base on coin | H30: ● | I30: integer | L30: Default is 1
B31: 2 | C31: rate | D31: Rate | H31: ● | I31: integer
B38: Table Name ： | D38: T_AD_CoinRate_History
B40: No | C40: Field Name | D40: Description | F40: PK | G40: AI | H40: NN | I40: Type | J40: Length | K40: FK | L40: Remark
B41: 1 | C41: old_base | D41: Old Base Coin | H41: ● | I41: integer | L41: Default is 1
B42: 2 | C42: new_base | D42: New Base Coin | H42: ● | I42: integer
B43: 3 | C43: old_rate | D43: Old Rate | H43: ● | I43: integer
B44: 4 | C44: new_rate | D44: New Rate | H44: ● | I44: integer
B45: 5 | C45: change_by | D45: Change By | H45: ● | I45: Bigint | K45: ● | L45: M_AD_Login ID
B46: 6 | C46: change_note | D46: Change reason or Description | H46: ● | I46: varchar
B50: Table Name ： | D50: T_AD_Order
B52: No | C52: Field Name | D52: Description | F52: PK | G52: AI | H52: NN | I52: Type | J52: Length | K52: FK | L52: Remark
B53: 1 | C53: customer_id | D53: Customer ID | H53: ● | I53: Bigint | K53: ● | L53: T_CU_Customer ID
B54: 2 | C54: payment | D54: Payment Type | H54: ● | I54: integer | L54: 0:Coin,1:COD
B55: 3 | C55: township_id | D55: Delivery Township ID | H55: ● | I55: integer | L55: M_Township ID
B56: 4 | C56: grandtotal_coin | D56: If Customer Buy with Coin | I56: integer | L56: Either or
B57: 5 | C57: grandtotal_cash | D57: If Customer Buy with COD | I57: integer
B58: 6 | C58: order_status | D58: Order Status | H58: ● | I58: integer | L58: M_Order_Status ID
B59: 7 | C59: order_date | D59: Order Date | H59: ● | I59: date
B60: 8 | C60: order_time | D60: Order Time | H60: ● | I60: time
B61: 9 | C61: last_control_by | D61: Last time Control By | H61: ● | I61: Bigint | K61: ● | L61: M_AD_Login ID
B65: Table Name ： | D65: T_AD_OrderDetail
B67: No | C67: Field Name | D67: Description | F67: PK | G67: AI | H67: NN | I67: Type | J67: Length | K67: FK | L67: Remark
B68: 1 | C68: order_id | D68: Order ID | H68: ● | I68: Bigint | K68: ● | L68: T_AD_Order ID
B69: 2 | C69: product_id | D69: Product ID | H69: ● | I69: integer
B70: 3 | C70: quantity | D70: Quantity | H70: ● | I70: integer
B71: 4 | C71: total_coin | D71: If Customer Buy with Coin | I71: integer | L71: Either or
B72: 5 | C72: total_cash | D72: If Customer Buy with COD | I72: integer
B73: 6 | C73: note | D73: add note by customer | I73: varchar | J73: 255
B77: Table Name ： | D77: T_AD_CoinCharge
B79: No | C79: Field Name | D79: Description | F79: PK | G79: AI | H79: NN | I79: Type | J79: Length | K79: FK | L79: Remark
B80: 1 | C80: customer_id | D80: Customer ID | H80: ● | I80: Bigint | K80: ● | L80: T_CU_Customer ID
B81: 2 | C81: request_coin | D81: Customer Request Coin | H81: ● | I81: integer
B82: 3 | C82: request_evd_ID | D82: Payment Screenshot | H82: ● | I82: Bigint | K82: ● | L82: T_AD_Evd ID
B83: 4 | C83: request_datetime | D83: Requested Datetime | H83: ● | I83: timestamp
B84: 5 | C84: decision_status | D84: Status | H84: ● | I84: integer | L84: M_Decision_Status ID
B85: 6 | C85: re_decision | D85: Re-decision or not | H85: ● | I85: integer | L85: 0:false,1:true
B86: 7 | C86: decision_by | D86: Decision By | H86: ● | I86: Bigint | K86: ● | L86: M_AD_Login ID
B91: Table Name ： | D91: T_AD_CoinCharge_Decision_History
B93: No | C93: Field Name | D93: Description | F93: PK | G93: AI | H93: NN | I93: Type | J93: Length | K93: FK | L93: Remark
B94: 1 | C94: charge_id | D94: Coin Charge ID | H94: ● | I94: Bigint | K94: ● | L94: T_AD_Charge ID
B95: 2 | C95: decision_by | D95: Decision By | H95: ● | I95: Bigint | K95: ● | L95: M_AD_Login ID
B96: 3 | C96: old_status | D96: Old Status | H96: ● | I96: integer
B97: 4 | C97: new_status | D97: New Status | H97: ● | I97: integer
B98: 5 | C98: note | D98: Note by Admin | I98: varchar | J98: 255
B102: Table Name ： | D102: T_CU_Coin_Customer_History
B104: No | C104: Field Name | D104: Description | F104: PK | G104: AI | H104: NN | I104: Type | J104: Length | K104: FK | L104: Remark
B105: 1 | C105: customer_id | D105: Customer ID | H105: ● | I105: Bigint | K105: ● | L105: T_CU_Customer ID
B106: 2 | C106: add_coin | D106: Add Coin | H106: ● | I106: integer
B107: 3 | C107: balance_coin | D107: Coin Balance | H107: ● | I107: integer
B108: 4 | C108: approve_By | D108: Approve By | H108: ● | I108: integer | L108: M_AD_Login ID
B109: 5 | C109: note | D109: Note | I109: varchar
B110: 6 | C110: by_action | L110: 0:Charge,1:Add Directly
B113: Table Name ： | D113: T_AD_CoinCharge_Finance
B115: No | C115: Field Name | D115: Description | F115: PK | G115: AI | H115: NN | I115: Type | J115: Length | K115: FK | L115: Remark
B116: 1 | C116: charge_id | D116: Coin Charge ID | H116: ● | I116: Bigint | K116: ● | L116: T_AD_Charge ID
B117: 2 | C117: payment_type | D117: Payment Type | H117: ● | I117: integer | L117: M_Payment ID
B118: 3 | C118: amount | D118: Received Amount | H118: ● | I118: integer
B121: Table Name ： | D121: M_CU_Customer_Login
B123: No | C123: Field Name | D123: Description | F123: PK | G123: AI | H123: NN | I123: Type | J123: Length | K123: FK | L123: Remark
B124: 1 | C124: email | D124: Email | F124: ● | H124: ● | I124: varchar | J124: 128
B125: 2 | C125: password | D125: Password | H125: ● | I125: varchar | J125: 40 | K125: 128
B126: 3 | C126: verify | D126: Valid or not | H126: ● | I126: integer | L126: 0:Not Valid,1:Valid
B127: 4 | C127: verift_code | D127: Verify_Code | H127: ● | I127: varchar | J127: 128 | L127: generate with [A-Za-z0-9!#$%&]
B128: 5 | C128: customer_id | D128: Customer ID | H128: ● | I128: Bigint | K128: ● | L128: T_CU_Customer ID
B129: 6 | C129: last_login_time | D129: Last Login Time | H129: ● | I129: timestamp
B133: Table Name ： | D133: T_CU_Customer
B135: No | C135: Field Name | D135: Description | F135: PK | G135: AI | H135: NN | I135: Type | J135: Length | K135: FK | L135: Remark
B136: 1 | C136: customerID | D136: ID of Customer | F136: ● | H136: ● | I136: varchar | J136: 12 | L136: Generate Rule ------------------ 1=>Nickname (First Letter) 2=>Nickname (Last Letter) 3=>email (First letter) 4=>password (First Letter) 5=>password (Last Letter) 6,7=>date (dd) 8,9=>time (hh) 10,11,12=>Random Chararacter[A-Za-z0-9!#$%&]
B137: 2 | C137: bio | D137: Bio of customer | I137: varchar | J137: 255
B138: 3 | C138: nickname | D138: Nickname | H138: ● | I138: varchar | J138: 30
B139: 4 | C139: phone | D139: Phone | I139: varchar | J139: 20
B140: 5 | C140: address1 | D140: Address | I140: integer | L140: M_State ID
B141: 6 | C141: address2 | D141: Address | I141: integer | L141: M_Township ID
B142: 7 | C142: address3 | D142: Address | I142: varchar | J142: 128
B143: 8 | C143: login_by_facebook | D143: ID of Facebook Login | I143: varchar | J143: 255 | L143: Return Code form Facebook
B144: 9 | C144: login_by_gmail | D144: ID of Gmail Login | I144: varchar | J144: 255 | L144: Return Code form Google
B145: 10 | C145: dob | D145: Date of birthday | I145: timestamp
B146: 11 | C146: gender | D146: Gender of customer | I146: integer | L146: 0:Male,1:Female,2:Other
B147: 12 | C147: fav_type | D147: Favorite Type of Customer | I147: integer | L147: M_Fav_Type ID
B148: 13 | C148: taste | D148: Taste of Customer | I148: integer | L148: M_Taste ID
B149: 14 | C149: allergic | D149: Allergic of Customer | I149: varchar | J149: 255
...
